MANIFEST.in
README.md
setup.cfg
setup.py
biota/IO.py
biota/SM.py
biota/__init__.py
biota/calibrate.py
biota/change.py
biota/core.py
biota/download.py
biota/filter.py
biota/indices.py
biota/mask.py
biota.egg-info/PKG-INFO
biota.egg-info/SOURCES.txt
biota.egg-info/dependency_links.txt
biota.egg-info/not-zip-safe
biota.egg-info/top_level.txt