Metadata-Version: 1.0
Name: biota
Version: 0.2
Summary: Tools to generate aboveground biomass forest change maps from ALOS PALSAR/PALSAR-2 mosaic data.
Home-page: https://bitbucket.org/sambowers/biota
Author: Samuel Bowers
Author-email: sam.bowers@ed.ac.uk
License: GNU General Public License
Platform: UNKNOWN
